{
  "subreddit_id": "t5_2qh23",
  "banned_by": null,
  "removal_reason": null,
  "link_id": "t3_5m4am9",
  "likes": true,
  "replies": {
    "kind": "Listing",
    "data": {
      "modhash": "58m607a9w66d8360e31d17ddf99e58a7664cde8e8673dc1915",
      "children": [
        {
          "kind": "t1",
          "data": {
            "subreddit_id": "t5_2qh23",
            "banned_by": null,
            "removal_reason": null,
            "link_id": "t3_5m4am9",
            "likes": true,
            "replies": {
              "kind": "Listing",
              "data": {
                "modhash": "58m607a9w66d8360e31d17ddf99e58a7664cde8e8673dc1915",
                "children": [
                  {
                    "kind": "t1",
                    "data": {
                      "subreddit_id": "t5_2qh23",
                      "banned_by": null,
                      "removal_reason": null,
                      "link_id": "t3_5m4am9",
                      "likes": true,
                      "replies": "",
                      "user_reports": [],
                      "saved": false,
                      "id": "dc0pq4h",
                      "gilded": 0,
                      "archived": false,
                      "report_reasons": null,
                      "author": "magnanamos",
                      "parent_id": "t1_dc0ppjg",
                      "score": 1,
                      "approved_by": null,
                      "controversiality": 0,
                      "body": "3a",
                      "edited": false,
                      "author_flair_css_class": null,
                      "downs": 0,
                      "body_html": "&lt;div class=\"md\"&gt;&lt;p&gt;3a&lt;/p&gt;\n&lt;/div&gt;",
                      "stickied": false,
                      "subreddit": "test",
                      "score_hidden": false,
                      "name": "t1_dc0pq4h",
                      "created": 1483619555,
                      "author_flair_text": null,
                      "created_utc": 1483590755,
                      "ups": 1,
                      "mod_reports": [],
                      "num_reports": null,
                      "distinguished": null
                    }
                  }
                ],
                "after": null,
                "before": null
              }
            },
            "user_reports": [],
            "saved": false,
            "id": "dc0ppjg",
            "gilded": 0,
            "archived": false,
            "report_reasons": null,
            "author": "magnanamos",
            "parent_id": "t1_dc0ppb3",
            "score": 1,
            "approved_by": null,
            "controversiality": 0,
            "body": "2 a",
            "edited": false,
            "author_flair_css_class": null,
            "downs": 0,
            "body_html": "&lt;div class=\"md\"&gt;&lt;p&gt;2 a&lt;/p&gt;\n&lt;/div&gt;",
            "stickied": false,
            "subreddit": "test",
            "score_hidden": false,
            "name": "t1_dc0ppjg",
            "created": 1483619531,
            "author_flair_text": null,
            "created_utc": 1483590731,
            "ups": 1,
            "mod_reports": [],
            "num_reports": null,
            "distinguished": null
          }
        },
        {
          "kind": "t1",
          "data": {
            "subreddit_id": "t5_2qh23",
            "banned_by": null,
            "removal_reason": null,
            "link_id": "t3_5m4am9",
            "likes": null,
            "replies": {
              "kind": "Listing",
              "data": {
                "modhash": "58m607a9w66d8360e31d17ddf99e58a7664cde8e8673dc1915",
                "children": [
                  {
                    "kind": "t1",
                    "data": {
                      "subreddit_id": "t5_2qh23",
                      "banned_by": null,
                      "removal_reason": null,
                      "link_id": "t3_5m4am9",
                      "likes": null,
                      "replies": "",
                      "user_reports": [],
                      "saved": false,
                      "id": "dc0ps0p",
                      "gilded": 0,
                      "archived": false,
                      "report_reasons": null,
                      "author": "mrlamb",
                      "parent_id": "t1_dc0prtq",
                      "score": 1,
                      "approved_by": null,
                      "controversiality": 0,
                      "body": "3b",
                      "edited": false,
                      "author_flair_css_class": null,
                      "downs": 0,
                      "body_html": "&lt;div class=\"md\"&gt;&lt;p&gt;3b&lt;/p&gt;\n&lt;/div&gt;",
                      "stickied": false,
                      "subreddit": "test",
                      "score_hidden": false,
                      "name": "t1_dc0ps0p",
                      "created": 1483619631,
                      "author_flair_text": null,
                      "created_utc": 1483590831,
                      "ups": 1,
                      "mod_reports": [],
                      "num_reports": null,
                      "distinguished": null
                    }
                  }
                ],
                "after": null,
                "before": null
              }
            },
            "user_reports": [],
            "saved": false,
            "id": "dc0prtq",
            "gilded": 0,
            "archived": false,
            "report_reasons": null,
            "author": "mrlamb",
            "parent_id": "t1_dc0ppb3",
            "score": 1,
            "approved_by": null,
            "controversiality": 0,
            "body": "2 b",
            "edited": false,
            "author_flair_css_class": null,
            "downs": 0,
            "body_html": "&lt;div class=\"md\"&gt;&lt;p&gt;2 b&lt;/p&gt;\n&lt;/div&gt;",
            "stickied": false,
            "subreddit": "test",
            "score_hidden": false,
            "name": "t1_dc0prtq",
            "created": 1483619623,
            "author_flair_text": null,
            "created_utc": 1483590823,
            "ups": 1,
            "mod_reports": [],
            "num_reports": null,
            "distinguished": null
          }
        }
      ],
      "after": null,
      "before": null
    }
  },
  "user_reports": [],
  "saved": false,
  "id": "dc0ppb3",
  "gilded": 0,
  "archived": false,
  "report_reasons": null,
  "author": "magnanamos",
  "parent_id": "t3_5m4am9",
  "score": 1,
  "approved_by": null,
  "controversiality": 0,
  "body": "1",
  "edited": false,
  "author_flair_css_class": null,
  "downs": 0,
  "body_html": "&lt;div class=\"md\"&gt;&lt;p&gt;1&lt;/p&gt;\n&lt;/div&gt;",
  "stickied": false,
  "subreddit": "test",
  "score_hidden": false,
  "name": "t1_dc0ppb3",
  "created": 1483619522,
  "author_flair_text": null,
  "created_utc": 1483590722,
  "ups": 1,
  "mod_reports": [],
  "num_reports": null,
  "distinguished": null
}
